a2perf/__init__.py
a2perf/constants.py
a2perf/analysis/__init__.py
a2perf/analysis/evaluation.py
a2perf/analysis/expertise.py
a2perf/analysis/metrics.py
a2perf/analysis/metrics_lib.py
a2perf/analysis/reliability.py
a2perf/analysis/results.py
a2perf/analysis/system.py
a2perf/data/__init__.py
a2perf/data/combine.py
a2perf/data/generate.py
a2perf/data/minari_dataset/__init__.py
a2perf/data/minari_dataset/data_utils.py
a2perf/data/minari_dataset/tf_utils.py
a2perf/domains/__init__.py
a2perf/domains/tfa/__init__.py
a2perf/domains/tfa/gym_wrapper.py
a2perf/domains/tfa/suite_gym.py
a2perf/domains/tfa/utils.py
a2perf/launch/__init__.py
a2perf/launch/docker_utils.py
a2perf/launch/entrypoint.py
a2perf/metrics/__init__.py
a2perf/submission/__init__.py
a2perf/submission/main_submission.py
a2perf/submission/submission_util.py
a2perf/submission/configs/circuit_training/generalization.gin
a2perf/submission/configs/circuit_training/train.gin
a2perf/submission/configs/circuit_training/ariane/inference.gin
a2perf/submission/configs/circuit_training/toy_macro_stdcell/inference.gin
a2perf/submission/configs/quadruped_locomotion/generalization.gin
a2perf/submission/configs/quadruped_locomotion/inference.gin
a2perf/submission/configs/quadruped_locomotion/train.gin
a2perf/submission/configs/quadruped_locomotion/dog_pace/domain.gin
a2perf/submission/configs/quadruped_locomotion/dog_pace/inference.gin
a2perf/submission/configs/quadruped_locomotion/dog_spin/domain.gin
a2perf/submission/configs/quadruped_locomotion/dog_spin/inference.gin
a2perf/submission/configs/quadruped_locomotion/dog_trot/domain.gin
a2perf/submission/configs/quadruped_locomotion/dog_trot/inference.gin
a2perf/submission/configs/web_navigation/generalization.gin
a2perf/submission/configs/web_navigation/train.gin
a2perf/submission/configs/web_navigation/difficulty_level_1_num_websites_1/inference.gin
a2perf/submission/configs/web_navigation/difficulty_level_1_num_websites_10/inference.gin
a2perf-0.1.0.dist-info/LICENSE
a2perf-0.1.0.dist-info/METADATA
a2perf-0.1.0.dist-info/WHEEL
a2perf-0.1.0.dist-info/entry_points.txt
a2perf-0.1.0.dist-info/top_level.txt
a2perf-0.1.0.dist-info/RECORD
