Metadata-Version: 2.1
Name: a2perf
Version: 0.1.0
Summary: Benchmarking suite for evaluating autonomous agents in real-world domains.
Author-email: Farama Foundation <contact@farama.org>
License: MIT License
Project-URL: Homepage, https://farama.org
Project-URL: Repository, https://github.com/Farama-Foundation/A2Perf
Project-URL: Documentation, https://a2perf.farama.org
Project-URL: Bug Report, https://github.com/Farama-Foundation/A2Perf/issues
Keywords: Reinforcement Learning,Autonomous Agents,RL,Imitation Learning,Benchmark,AI
Classifier: Development Status :: 4 - Beta
Classifier: License :: OSI Approved :: MIT License
Classifier: Programming Language :: Python :: 3
Classifier: Programming Language :: Python :: 3.8
Classifier: Programming Language :: Python :: 3.9
Classifier: Programming Language :: Python :: 3.10
Classifier: Programming Language :: Python :: 3.11
Classifier: Intended Audience :: Science/Research
Classifier: Topic :: Scientific/Engineering :: Artificial Intelligence
Requires-Python: >=3.8
License-File: LICENSE
Requires-Dist: gin-config
Requires-Dist: gymnasium
Requires-Dist: minari
Requires-Dist: absl-py
Requires-Dist: codecarbon
Provides-Extra: all
Requires-Dist: torch==1.13.1; extra == "all"
Requires-Dist: tensorflow<2.16.1; extra == "all"
Requires-Dist: tf-agents; extra == "all"
Requires-Dist: timeout-decorator; extra == "all"
Requires-Dist: matplotlib; extra == "all"
Requires-Dist: cairocffi; extra == "all"
Requires-Dist: shapely; extra == "all"
Requires-Dist: selenium; extra == "all"
Requires-Dist: regex; extra == "all"
Requires-Dist: chromedriver-py; extra == "all"
Requires-Dist: pybullet; extra == "all"
Provides-Extra: circuit-training
Requires-Dist: torch==1.13.1; extra == "circuit-training"
Requires-Dist: tensorflow<2.16.1; extra == "circuit-training"
Requires-Dist: tf-agents; extra == "circuit-training"
Requires-Dist: timeout-decorator; extra == "circuit-training"
Requires-Dist: matplotlib; extra == "circuit-training"
Requires-Dist: cairocffi; extra == "circuit-training"
Requires-Dist: shapely; extra == "circuit-training"
Provides-Extra: quadruped-locomotion
Requires-Dist: pybullet; extra == "quadruped-locomotion"
Requires-Dist: scipy; extra == "quadruped-locomotion"
Provides-Extra: web-navigation
Requires-Dist: selenium; extra == "web-navigation"
Requires-Dist: regex; extra == "web-navigation"
Requires-Dist: chromedriver-py; extra == "web-navigation"
